README.md
setup.cfg
setup.py
pattern_matching/__init__.py
pattern_matching/auto_lookup.py
pattern_matching/full_magic.py
pattern_matching/injecting.py
pattern_matching/match_args_data.py
pattern_matching/no_magic.py
pattern_matching/pattern_engine.py
pattern_matching/withhacks.py
pattern_matching_pep634.egg-info/PKG-INFO
pattern_matching_pep634.egg-info/SOURCES.txt
pattern_matching_pep634.egg-info/dependency_links.txt
pattern_matching_pep634.egg-info/requires.txt
pattern_matching_pep634.egg-info/top_level.txt