Metadata-Version: 2.1
Name: pattern-matching-pep634
Version: 0.2.0
Summary: Pattern matching, backport of PEP-634
Home-page: https://github.com/MegaIng/pattern-matching
Author: MegaIng
Author-email: trampchamp@hotmail.de
License: UNKNOWN
Project-URL: Bug Reports, https://github.com/MegaIng/pattern-matching/issues
Project-URL: Source, https://github.com/MegaIng/pattern-matching/
Keywords: pattern-matching,PEP-634,backport
Platform: UNKNOWN
Classifier: Development Status :: 3 - Alpha
Classifier: Intended Audience :: Developers
Classifier: Topic :: Software Development
Classifier: License :: OSI Approved :: MIT License
Classifier: Programming Language :: Python :: 3
Classifier: Programming Language :: Python :: 3.7
Classifier: Programming Language :: Python :: 3.8
Classifier: Programming Language :: Python :: 3.9
Classifier: Programming Language :: Python :: 3 :: Only
Classifier: Programming Language :: Python :: Implementation :: CPython
Requires-Python: >=3.7
